gxkit/__init__.py
gxkit/py.typed
gxkit/core/__init__.py
gxkit/core/loader.py
gxkit/core/version.py
gxkit/dbtools/__init__.py
gxkit/dbtools/dbclient.py
gxkit-0.1.1.post3.dist-info/licenses/LICENSE
gxkit-0.1.1.post3.dist-info/METADATA
gxkit-0.1.1.post3.dist-info/WHEEL
gxkit-0.1.1.post3.dist-info/top_level.txt
gxkit-0.1.1.post3.dist-info/RECORD
