Metadata-Version: 2.4
Name: gxkit
Version: 0.1.1.post3
Summary: Gx Company development toolkit
Author-email: Shaojiayi <shaojy@sunburst.com.cn>
License: Apache-2.0
Requires-Python: >=3.8
License-File: LICENSE
Requires-Dist: pyyaml
Dynamic: license-file
